MANIFEST.in
README
__init__.py
__pkginfo__.py
entities.py
hooks.py
schema.py
setup.py
site_cubicweb.py
testutils.py
views.py
cubicweb_mercurial_server.egg-info/PKG-INFO
cubicweb_mercurial_server.egg-info/SOURCES.txt
cubicweb_mercurial_server.egg-info/dependency_links.txt
cubicweb_mercurial_server.egg-info/not-zip-safe
cubicweb_mercurial_server.egg-info/requires.txt
cubicweb_mercurial_server.egg-info/top_level.txt
i18n/de.po
i18n/en.po
i18n/es.po
i18n/fr.po
migration/0.2.3_Any.py
migration/0.3.0_Any.py
migration/0.4.0_Any.py
migration/0.6.0_Any.py
migration/0.7.0_Any.py
migration/0.7.2_Any.py
migration/postcreate.py
test/__init__.py
test/pytestconf.py
test/unittest_entities.py
test/unittest_hooks.py
test/unittest_security.py