Metadata-Version: 1.0
Name: cubicweb-mercurial-server
Version: 0.7.2
Summary: mercurial server integration cube
Home-page: http://www.cubicweb.org/project/cubicweb-mercurial-server
Author: Florent Cayré (FRANCE)
Author-email: florent.cayre@gmail.com
License: LGPL
Platform: UNKNOWN
